{
    "date": "2025-09-22",
    "timestamp": 1758546502.981139,
    "total_numbers": 255,
    "formatted_numbers": [
        "049",
        "615",
        "458",
        "508",
        "725",
        "448",
        "997",
        "062",
        "188",
        "819",
        "333",
        "617",
        "949",
        "880",
        "718",
        "191",
        "237",
        "085",
        "579",
        "110",
        "020",
        "800",
        "698",
        "788",
        "697",
        "115",
        "948",
        "445",
        "656",
        "927",
        "019",
        "512",
        "218",
        "943",
        "037",
        "055",
        "292",
        "409",
        "822",
        "557",
        "403",
        "757",
        "759",
        "422",
        "756",
        "624",
        "021",
        "084",
        "541",
        "540",
        "497",
        "016",
        "487",
        "253",
        "974",
        "147",
        "795",
        "846",
        "433",
        "770",
        "407",
        "881",
        "898",
        "739",
        "395",
        "068",
        "831",
        "947",
        "545",
        "787",
        "723",
        "109",
        "484",
        "502",
        "456",
        "260",
        "119",
        "619",
        "302",
        "504",
        "715",
        "405",
        "436",
        "468",
        "206",
        "301",
        "252",
        "283",
        "776",
        "167",
        "780",
        "631",
        "821",
        "726",
        "081",
        "696",
        "279",
        "295",
        "581",
        "699",
        "775",
        "492",
        "651",
        "376",
        "868",
        "596",
        "642",
        "449",
        "104",
        "826",
        "784",
        "065",
        "608",
        "245",
        "213",
        "282",
        "503",
        "344",
        "498",
        "820",
        "794",
        "043",
        "154",
        "605",
        "999",
        "734",
        "063",
        "667",
        "978",
        "840",
        "992",
        "966",
        "137",
        "338",
        "678",
        "046",
        "089",
        "469",
        "346",
        "201",
        "894",
        "733",
        "446",
        "182",
        "542",
        "363",
        "396",
        "576",
        "550",
        "025",
        "190",
        "535",
        "139",
        "116",
        "869",
        "931",
        "793",
        "573",
        "080",
        "754",
        "006",
        "071",
        "400",
        "187",
        "645",
        "234",
        "844",
        "176",
        "417",
        "762",
        "491",
        "664",
        "765",
        "178",
        "890",
        "467",
        "207",
        "096",
        "643",
        "226",
        "478",
        "804",
        "912",
        "751",
        "354",
        "264",
        "031",
        "148",
        "300",
        "254",
        "586",
        "421",
        "952",
        "488",
        "827",
        "129",
        "867",
        "675",
        "048",
        "641",
        "040",
        "018",
        "646",
        "125",
        "951",
        "583",
        "106",
        "858",
        "560",
        "093",
        "483",
        "370",
        "007",
        "884",
        "460",
        "876",
        "883",
        "509",
        "572",
        "459",
        "823",
        "361",
        "694",
        "388",
        "924",
        "944",
        "995",
        "555",
        "671",
        "161",
        "719",
        "117",
        "360",
        "401",
        "589",
        "760",
        "928",
        "547",
        "410",
        "199",
        "575",
        "741",
        "887",
        "857",
        "875",
        "935",
        "609",
        "975",
        "769",
        "416",
        "522",
        "441",
        "711",
        "558",
        "289"
    ],
    "model_info": {
        "type": "raw_numbers",
        "temperature": 3.0,
        "top_k": 10,
        "unique_count": 255
    }
}